{
	"format_version": "1.21.6",
	"credit": "Made with Blockbench",
	"texture_size": [32, 32],
	"textures": {
		"0": "fathoms:block/aberration_idol/odd",
		"particle": "item/poisonous_potato"
	},
	"elements": [
		{
			"from": [7.2095, -16, 5.8995],
			"to": [7.6095, -15.4, 6.2995],
			"rotation": {"angle": 0, "axis": "y", "origin": [7.6, -16, 5.9]},
			"faces": {
				"north": {"uv": [9, 8.05, 8, 11.05], "texture": "#0"},
				"east": {"uv": [8, 8, 9, 11], "texture": "#0"},
				"south": {"uv": [10, 8, 9, 11], "texture": "#0"},
				"west": {"uv": [9, 8.05, 8, 11.05], "texture": "#0"},
				"up": {"uv": [9, 6, 8, 8], "texture": "#0"},
				"down": {"uv": [10, 6, 9, 8], "texture": "#0"}
			}
		},
		{
			"from": [7.21, -16, 6.8],
			"to": [7.61, -15.4, 7.2],
			"rotation": {"angle": 0, "axis": "y", "origin": [7.6, -16, 7.2]},
			"faces": {
				"north": {"uv": [9, 8, 10, 11], "texture": "#0"},
				"east": {"uv": [9, 8, 8, 11], "texture": "#0"},
				"south": {"uv": [8, 8.05, 9, 11.05], "texture": "#0"},
				"west": {"uv": [8, 8.05, 9, 11.05], "texture": "#0"},
				"up": {"uv": [9, 8, 8, 6], "texture": "#0"},
				"down": {"uv": [10, 8, 9, 6], "texture": "#0"}
			}
		},
		{
			"from": [8.3895, -16, 5.8995],
			"to": [8.7895, -15.4, 6.2995],
			"rotation": {"angle": 0, "axis": "y", "origin": [8.4, -16, 5.9]},
			"faces": {
				"north": {"uv": [8, 8.05, 9, 11.05], "texture": "#0"},
				"east": {"uv": [8, 8.05, 9, 11.05], "texture": "#0"},
				"south": {"uv": [9, 8, 10, 11], "texture": "#0"},
				"west": {"uv": [9, 8, 8, 11], "texture": "#0"},
				"up": {"uv": [8, 6, 9, 8], "texture": "#0"},
				"down": {"uv": [9, 6, 10, 8], "texture": "#0"}
			}
		},
		{
			"from": [8.39, -16, 6.8],
			"to": [8.79, -15.4, 7.2],
			"rotation": {"angle": 0, "axis": "y", "origin": [8.4, -16, 7.2]},
			"faces": {
				"north": {"uv": [10, 8, 9, 11], "texture": "#0"},
				"east": {"uv": [9, 8.05, 8, 11.05], "texture": "#0"},
				"south": {"uv": [9, 8.05, 8, 11.05], "texture": "#0"},
				"west": {"uv": [8, 8, 9, 11], "texture": "#0"},
				"up": {"uv": [8, 8, 9, 6], "texture": "#0"},
				"down": {"uv": [9, 8, 10, 6], "texture": "#0"}
			}
		},
		{
			"from": [7.5, -15.6, 5.9],
			"to": [8.5, -14.6, 7.1],
			"rotation": {"angle": 0, "axis": "y", "origin": [7.5, -15.6, 5.9]},
			"faces": {
				"north": {"uv": [0, 6, 2.5, 11], "texture": "#0"},
				"east": {"uv": [5.5, 6, 2.5, 11], "texture": "#0"},
				"south": {"uv": [0, 6, 2.5, 11], "texture": "#0"},
				"west": {"uv": [2.5, 6, 5.5, 11], "texture": "#0"},
				"up": {"uv": [0, 0, 2.5, 6], "texture": "#0"},
				"down": {"uv": [2.5, 0, 5, 6], "texture": "#0"}
			}
		},
		{
			"from": [7.6, -16, 6],
			"to": [8.4, -15.6, 7],
			"rotation": {"angle": 0, "axis": "y", "origin": [7.6, -16, 6]},
			"faces": {
				"north": {"uv": [5.5, 6, 7.5, 8], "texture": "#0"},
				"east": {"uv": [8, 6, 5.5, 8], "texture": "#0"},
				"south": {"uv": [5.5, 6, 7.5, 8], "texture": "#0"},
				"west": {"uv": [5.5, 6, 8, 8], "texture": "#0"},
				"down": {"uv": [5.5, 8, 7.5, 13], "texture": "#0"}
			}
		},
		{
			"name": "abel",
			"from": [7.4, -16, 5.5],
			"to": [8, -15.4, 6.1],
			"rotation": {"angle": 22.5, "axis": "y", "origin": [8, -15.7, 5.8]},
			"faces": {
				"north": {"uv": [5, 3, 6.5, 6], "texture": "#0"},
				"east": {"uv": [8, 3, 6.5, 6], "texture": "#0"},
				"west": {"uv": [6.5, 3, 8, 6], "texture": "#0"},
				"up": {"uv": [11, 3, 9.5, 0], "texture": "#0"},
				"down": {"uv": [8, 3, 9.5, 6], "texture": "#0"}
			}
		},
		{
			"name": "cain",
			"from": [8, -16, 5.5],
			"to": [8.6, -15.4, 6.1],
			"rotation": {"angle": -22.5, "axis": "y", "origin": [8, -15.7, 5.8]},
			"faces": {
				"north": {"uv": [6.5, 0, 5, 3], "texture": "#0"},
				"east": {"uv": [8, 0, 6.5, 3], "texture": "#0"},
				"west": {"uv": [6.5, 0, 8, 3], "texture": "#0"},
				"up": {"uv": [9.5, 3, 11, 0], "texture": "#0"},
				"down": {"uv": [9.5, 0, 8, 3], "texture": "#0"}
			}
		},
		{
			"from": [7.902, -14.598, 6.002],
			"to": [8.098, -14.202, 6.998],
			"rotation": {"angle": 0, "axis": "y", "origin": [8, -14.4, 6.5]},
			"faces": {
				"north": {"uv": [10.5, 3, 11.5, 4], "rotation": 90, "texture": "#0"},
				"east": {"uv": [10.5, 4, 11.5, 9], "rotation": 90, "texture": "#0"},
				"south": {"uv": [11.5, 3, 12.5, 4], "rotation": 270, "texture": "#0"},
				"west": {"uv": [11.5, 4, 10.5, 9], "rotation": 270, "texture": "#0"},
				"up": {"uv": [10.5, 9, 10, 4], "rotation": 180, "texture": "#0"},
				"down": {"uv": [12, 9, 11.5, 4], "texture": "#0"}
			}
		}
	],
	"display": {
		"thirdperson_righthand": {
			"rotation": [75, 45, 0],
			"translation": [0, 2.5, 0],
			"scale": [0.375, 0.375, 0.375]
		},
		"thirdperson_lefthand": {
			"rotation": [75, 45, 0],
			"translation": [0, 2.5, 0],
			"scale": [0.375, 0.375, 0.375]
		},
		"firstperson_righthand": {
			"rotation": [0, 45, 0],
			"scale": [0.4, 0.4, 0.4]
		},
		"firstperson_lefthand": {
			"rotation": [0, -135, 0],
			"scale": [0.4, 0.4, 0.4]
		},
		"ground": {
			"translation": [0, 3, 0],
			"scale": [0.25, 0.25, 0.25]
		},
		"gui": {
			"rotation": [30, -135, 0],
			"scale": [0.625, 0.625, 0.625]
		},
		"fixed": {
			"scale": [0.5, 0.5, 0.5]
		}
	}
}